{
  "AAD": [
    "1214",
    "2974",
    "4234"
  ],
  "AAEC": [
    "1005",
    "1006",
    "2104",
    "2434",
    "2974",
    "3004",
    "3014",
    "3024",
    "3204",
    "3314",
    "3324",
    "3424",
    "3454",
    "3604",
    "3974",
    "4204",
    "4314",
    "4414",
    "4434",
    "4464",
    "4484",
    "4504",
    "4804",
    "4814",
    "4964",
    "4974",
    "4994",
    "5044",
    "5074",
    "5104",
    "5126",
    "5134",
    "5484",
    "5804G",
    "5814G",
    "5894",
    "5904",
    "5974",
    "5994",
    "6004",
    "7994",
    "4135",
    "6564",
    "6304"
  ],
  "ACIS": [
    "1004",
    "1104",
    "1504",
    "2115",
    "2116",
    "2504",
    "3115",
    "3116",
    "3314",
    "3504",
    "3554",
    "4024",
    "4114",
    "4194",
    "4214",
    "4344",
    "4364",
    "4414",
    "4654",
    "4664",
    "4684",
    "4974",
    "4994",
    "5014",
    "5064",
    "5114G",
    "5334",
    "5364",
    "5424",
    "5504",
    "5524",
    "5584",
    "5614",
    "5654G",
    "5664",
    "5754",
    "5974",
    "5994",
    "7994",
    "4544",
    "5644",
    "6024"
  ],
  "ADV": [
    "2134",
    "3004",
    "3014",
    "3024",
    "4324",
    "5204",
    "2034",
    "3034"
  ],
  "AFST": [
    "1714",
    "1814",
    "2264",
    "2276",
    "2974",
    "4354",
    "4754",
    "4964",
    "4974",
    "4974H",
    "4994",
    "5314",
    "5974",
    "2204",
    "2754",
    "6234",
    "2644"
  ],
  "AHRM": [
    "1014",
    "2014",
    "2404"
  ],
  "AINS": [
    "1104",
    "2414",
    "2974",
    "3684",
    "4754",
    "4974",
    "4994"
  ],
  "ALCE": [
    "2094",
    "2414",
    "2484",
    "2964",
    "2974",
    "3004",
    "3494",
    "3624",
    "3634",
    "3900",
    "3954",
    "4044",
    "4054",
    "4064",
    "4244",
    "4754",
    "4964",
    "4974",
    "4994",
    "5224",
    "5814",
    "5904",
    "5964",
    "5974",
    "5994",
    "6416",
    "6974",
    "7964",
    "7994",
    "4024",
    "6436",
    "6984",
    "4234"
  ],
  "ALS": [
    "1004",
    "1014",
    "1024",
    "1234",
    "2304",
    "2604",
    "2964",
    "2974",
    "2994",
    "3104",
    "3204",
    "3954",
    "4574",
    "4614",
    "4814",
    "4964",
    "4974",
    "4994",
    "5024",
    "5094",
    "5104",
    "5404",
    "5904",
    "5954",
    "5964",
    "5974",
    "6314",
    "5214",
    "4554"
  ],
  "AOE": [
    "2024",
    "2074",
    "2104",
    "2114",
    "2664",
    "2974",
    "2994",
    "2994H",
    "3014",
    "3034",
    "3044",
    "3054B",
    "3054",
    "3114",
    "3124",
    "3134",
    "3144",
    "3154",
    "3164",
    "3234",
    "3264",
    "4054",
    "4064",
    "4066",
    "4084",
    "4106",
    "4114",
    "4166",
    "4174",
    "4206",
    "4244",
    "4266",
    "4324",
    "4366",
    "4404",
    "4454",
    "4634",
    "4674",
    "4974",
    "4994",
    "4994H",
    "5054",
    "5144",
    "5174",
    "5234",
    "5314",
    "5316",
    "5334",
    "5404",
    "5664",
    "5734",
    "5764",
    "5904",
    "5944",
    "5974",
    "5994",
    "6254",
    "6744",
    "6774",
    "6974",
    "7994",
    "4034",
    "4344",
    "4604",
    "5114",
    "6124",
    "6145",
    "6204",
    "6984",
    "6314",
    "5614",
    "5444G",
    "5034"
  ],
  "APS": [
    "2974",
    "2974H",
    "4974H",
    "4994H",
    "5974",
    "1704",
    "2434",
    "4414"
  ],
  "APSC": [
    "1454",
    "1464",
    "2004",
    "2104",
    "2114",
    "2164",
    "2424",
    "2524",
    "2624",
    "2964",
    "2974",
    "2994",
    "3134",
    "3334",
    "3434",
    "3524",
    "3624",
    "3954",
    "3964",
    "4004",
    "4204",
    "4424",
    "4444",
    "4464",
    "4514",
    "4554",
    "4954",
    "4964",
    "4974",
    "4994",
    "5004",
    "5154",
    "5184",
    "5244",
    "5254",
    "5334",
    "5404",
    "5514G",
    "5604",
    "5894",
    "5904",
    "5974",
    "5994",
    "7994",
    "3984",
    "4984",
    "2714",
    "3254",
    "2824",
    "5014",
    "2574",
    "3684",
    "2124",
    "5534"
  ],
  "ARBC": [
    "1105",
    "1106",
    "2105",
    "2106",
    "2774",
    "2974",
    "3106",
    "3124",
    "3274",
    "4154",
    "4334",
    "4974",
    "4994",
    "3105",
    "3304",
    "3644"
  ],
  "ARCH": [
    "1016",
    "1044",
    "2016",
    "3016",
    "3054",
    "3115",
    "3234",
    "4004",
    "4014",
    "4034",
    "4044",
    "4055",
    "4075",
    "4114",
    "4154",
    "4516",
    "4524",
    "4706",
    "4716",
    "4954",
    "4964",
    "4974",
    "4974H",
    "4994",
    "5036",
    "5044G",
    "5056",
    "5064",
    "5116",
    "5126",
    "5134",
    "5516",
    "5566",
    "5706",
    "5716",
    "5756",
    "5775G",
    "5894",
    "5904",
    "5974",
    "5994",
    "7994",
    "3066",
    "3204",
    "3504",
    "4224"
  ],
  "ART": [
    "1004",
    "1104",
    "1204",
    "1214",
    "1334",
    "1404",
    "1504",
    "1604",
    "2386",
    "2514",
    "2524",
    "2554",
    "2565",
    "2576",
    "2604",
    "2664",
    "2704",
    "2974",
    "3504",
    "3514",
    "3524",
    "3554",
    "3564",
    "3566",
    "3574",
    "3604",
    "3704",
    "3900",
    "4104",
    "4384",
    "4484",
    "4504",
    "4514",
    "4524",
    "4544",
    "4554",
    "4564",
    "4576",
    "4584",
    "4754",
    "4894",
    "4964",
    "4974",
    "5384",
    "5524",
    "5534",
    "5564G",
    "5604",
    "5704",
    "5854G",
    "5904",
    "5964",
    "5974",
    "5994",
    "1614",
    "3174",
    "5204"
  ],
  "AS": [
    "1116",
    "2116",
    "2934",
    "2944",
    "3216",
    "4216",
    "4974"
  ],
  "ASPT": [
    "5414",
    "5974",
    "6004",
    "6204",
    "7994",
    "5124",
    "5984"
  ],
  "AT": [
    "0124",
    "0194",
    "0224",
    "0274",
    "0324",
    "0354",
    "0374",
    "0404",
    "0414",
    "0444",
    "0464",
    "0484",
    "0514",
    "0524",
    "0544",
    "0554",
    "0564",
    "0624",
    "0674",
    "0694",
    "0704",
    "0974",
    "0494"
  ],
  "BC": [
    "2024",
    "2044",
    "2064",
    "2104",
    "2114",
    "2134",
    "2214",
    "2354",
    "3014",
    "3064",
    "3114",
    "3134",
    "4024",
    "4064",
    "4164",
    "4434",
    "4444",
    "4974",
    "4994",
    "5024",
    "5134",
    "5154",
    "5524",
    "5904",
    "5974",
    "5994",
    "1124",
    "4114",
    "5114G",
    "4364",
    "5374",
    "4374",
    "4124",
    "5124G"
  ],
  "BCHM": [
    "1024",
    "2024",
    "2354",
    "2364",
    "2974",
    "2974H",
    "2994",
    "3114",
    "3900",
    "4116",
    "4124",
    "4354",
    "4554",
    "4754",
    "4784",
    "4974",
    "4974H",
    "4994",
    "4994H",
    "5004",
    "5014",
    "5344",
    "5784G",
    "5974",
    "5994",
    "7994",
    "5024"
  ],
  "BDS": [
    "2006",
    "3134",
    "4194",
    "4864",
    "2005"
  ],
  "BIOL": [
    "1054",
    "1106",
    "1116",
    "1136",
    "2004",
    "2124",
    "2134",
    "2304",
    "2604",
    "2614",
    "2704",
    "2804",
    "2964",
    "2974",
    "2974H",
    "2994",
    "2994H",
    "3104",
    "3204",
    "3254",
    "3264",
    "3604",
    "3804",
    "3954",
    "4164",
    "4354",
    "4404",
    "4474",
    "4564",
    "4574",
    "4634",
    "4644",
    "4684",
    "4704",
    "4714",
    "4824",
    "4964",
    "4974",
    "4974H",
    "4994",
    "4994H",
    "5006",
    "5174",
    "5634",
    "5824",
    "5974",
    "5994",
    "6014",
    "6404",
    "7994",
    "5984",
    "2504",
    "4844",
    "5844",
    "5024",
    "5034",
    "5094",
    "5184",
    "6004",
    "4984",
    "4554"
  ],
  "BIT": [
    "2104",
    "2164",
    "2405",
    "2406",
    "2554",
    "3414",
    "3424",
    "3434",
    "3444",
    "3454",
    "3464",
    "3474",
    "3484",
    "3514",
    "3524",
    "3554",
    "3614",
    "3954",
    "4164",
    "4424",
    "4434",
    "4444",
    "4454",
    "4464",
    "4474",
    "4484",
    "4604",
    "4624",
    "4964",
    "4974",
    "4994",
    "5114",
    "5324",
    "5424",
    "5534",
    "5664",
    "5894",
    "5974",
    "5994",
    "6194",
    "6324",
    "6424",
    "7994",
    "3674",
    "4644",
    "4654",
    "4544",
    "5414",
    "5564",
    "5514"
  ],
  "BMES": [
    "2004",
    "2104",
    "2994",
    "3004",
    "3024",
    "3034",
    "3114",
    "3124",
    "3184",
    "3844",
    "3900",
    "4016",
    "4064",
    "4974",
    "4994",
    "4994H",
    "5024",
    "5064",
    "5514",
    "5574",
    "5904",
    "5944",
    "5974",
    "5994",
    "6064",
    "7994",
    "4574",
    "2074",
    "3154",
    "5305",
    "5724",
    "6164",
    "6554",
    "3224",
    "3164"
  ],
  "BMSP": [
    "2136",
    "2146",
    "4974",
    "4994"
  ],
  "BMVS": [
    "2994",
    "4974",
    "4994",
    "5014",
    "5174",
    "5194",
    "5224",
    "5244",
    "5274",
    "5284",
    "5324",
    "5624",
    "5764",
    "5794",
    "5944",
    "5974",
    "5994",
    "6014",
    "6064",
    "6074",
    "6084",
    "6094",
    "6534",
    "6724",
    "7994",
    "5114"
  ],
  "BSE": [
    "2304",
    "2994",
    "3144",
    "3334",
    "3504",
    "3524",
    "3534",
    "4126",
    "4344",
    "4394",
    "4554",
    "4974",
    "4994",
    "5244",
    "5344G",
    "5894",
    "5904",
    "5974",
    "5994",
    "7994",
    "4564",
    "5564G",
    "5944",
    "5124",
    "5534"
  ],
  "CEE": [
    "2804",
    "2814",
    "2834",
    "2974",
    "2994",
    "3014",
    "3104",
    "3274",
    "3304B",
    "3304",
    "3314",
    "3404",
    "3424",
    "3434",
    "3514B",
    "3514",
    "3604",
    "3684",
    "3804",
    "3814",
    "4014",
    "4074",
    "4114",
    "4134",
    "4264",
    "4274",
    "4284",
    "4344",
    "4384",
    "4394",
    "4404",
    "4534",
    "4544",
    "4554",
    "4654",
    "4804",
    "4824",
    "4844",
    "4974",
    "4994",
    "4994H",
    "5004",
    "5020",
    "5080",
    "5114",
    "5126",
    "5140",
    "5144",
    "5244",
    "5264",
    "5274",
    "5304",
    "5390",
    "5414",
    "5450",
    "5464",
    "5544",
    "5554",
    "5564",
    "5744",
    "5854G",
    "5894",
    "5904",
    "5944",
    "5974",
    "5994",
    "7994",
    "3954",
    "4334",
    "4614",
    "4634",
    "5160",
    "5664",
    "5784",
    "6434",
    "5640",
    "5054",
    "5874",
    "4624",
    "6104",
    "5604"
  ],
  "CEM": [
    "2104",
    "2404",
    "2824",
    "3024",
    "3074",
    "3084",
    "3134",
    "3154",
    "4024",
    "4445",
    "4446",
    "4624",
    "4634",
    "4974",
    "4994",
    "3714",
    "4724"
  ],
  "CHE": [
    "2004",
    "2114",
    "2164",
    "3015",
    "3114",
    "3124",
    "3134",
    "3144",
    "3154",
    "4186",
    "4404",
    "4904",
    "4974",
    "4994",
    "5904",
    "5944",
    "5974",
    "5994",
    "7994",
    "3185",
    "4015",
    "5094",
    "4214"
  ],
  "CHEM": [
    "1016",
    "1026",
    "1035",
    "1036",
    "1045",
    "1046",
    "2154",
    "2164",
    "2424",
    "2514",
    "2535",
    "2536",
    "2546",
    "2555",
    "2564",
    "2565",
    "2964",
    "2974",
    "2974H",
    "3615",
    "3616",
    "3625",
    "3684",
    "3900",
    "4014",
    "4074",
    "4114",
    "4414",
    "4424",
    "4514",
    "4544",
    "4554",
    "4616",
    "4634",
    "4684",
    "4734",
    "4964",
    "4974",
    "4974H",
    "4994",
    "4994H",
    "5174",
    "5414",
    "5424G",
    "5506",
    "5514G",
    "5535",
    "5614",
    "5706",
    "5894",
    "5904",
    "5914",
    "5944",
    "5974",
    "5994",
    "6434",
    "6914",
    "7994"
  ],
  "CHN": [
    "1106",
    "2106",
    "2964",
    "2974",
    "2974H",
    "3106",
    "3474",
    "4964",
    "4974",
    "4974H",
    "4994",
    "4994H",
    "3514",
    "3604"
  ],
  "CINE": [
    "2054",
    "2064",
    "3184",
    "3214",
    "3224",
    "3534",
    "3544",
    "4084",
    "4144"
  ],
  "CLA": [
    "2964",
    "4974",
    "4974H",
    "4994",
    "4994H",
    "2434",
    "1134",
    "2224",
    "2234",
    "2444"
  ],
  "CMDA": [
    "2005",
    "2006",
    "2014",
    "2994",
    "3605",
    "3606",
    "3634",
    "3654",
    "4314",
    "4654",
    "4664",
    "4864",
    "4974",
    "4994",
    "4604"
  ],
  "CMST": [
    "2064",
    "3044",
    "3064",
    "3124",
    "3214",
    "4714",
    "2034"
  ],
  "CNST": [
    "5084",
    "5124",
    "5214",
    "5424",
    "5624",
    "5634"
  ],
  "COMM": [
    "1004",
    "1014",
    "1016",
    "2004",
    "2014",
    "2024",
    "2084",
    "2094",
    "2124",
    "2764H",
    "2964",
    "2974H",
    "3954",
    "4024",
    "4204",
    "4964",
    "4974",
    "4994",
    "5034",
    "5894",
    "5904",
    "5974",
    "5994",
    "5024"
  ],
  "CONS": [
    "2304",
    "4324",
    "4964",
    "4974",
    "4994",
    "4304",
    "3404",
    "4414"
  ],
  "COS": [
    "1016",
    "2016",
    "2974",
    "3016",
    "4016",
    "4964",
    "4974",
    "4994",
    "5974"
  ],
  "CRIM": [
    "2754",
    "2964",
    "3414",
    "3434",
    "3474",
    "4424",
    "4454",
    "4754",
    "4974",
    "4994",
    "1054",
    "4474",
    "4484"
  ],
  "CS": [
    "1044",
    "1064",
    "1114",
    "1944",
    "2064",
    "2104",
    "2114",
    "2164",
    "2505",
    "2506",
    "2964",
    "2974",
    "3114",
    "3214",
    "3274",
    "3304",
    "3414",
    "3604",
    "3634",
    "3654",
    "3704",
    "3714",
    "3724",
    "3744",
    "3754",
    "3900",
    "4104",
    "4114",
    "4124",
    "4164",
    "4264",
    "4274",
    "4284",
    "4414",
    "4604",
    "4624",
    "4644",
    "4654",
    "4664",
    "4704",
    "4774",
    "4784",
    "4804",
    "4824",
    "4944",
    "4964",
    "4974",
    "4994",
    "5014",
    "5024",
    "5040",
    "5044",
    "5046",
    "5234",
    "5254",
    "5484",
    "5486",
    "5544",
    "5560",
    "5566",
    "5580",
    "5590",
    "5594",
    "5614",
    "5664",
    "5704",
    "5714",
    "5754",
    "5764",
    "5804",
    "5805",
    "5806",
    "5814",
    "5914",
    "5934",
    "5944",
    "5974",
    "5994",
    "6204",
    "6604",
    "6724",
    "6804",
    "7994",
    "5124",
    "5854",
    "5624",
    "6104",
    "5774",
    "4014",
    "1014",
    "2144",
    "4144",
    "2304",
    "5134",
    "4894"
  ],
  "CSES": [
    "2434",
    "3304",
    "3954",
    "4134",
    "4144",
    "4174",
    "4344",
    "4544",
    "4864",
    "5114",
    "5144",
    "5304",
    "5444",
    "5634",
    "5904",
    "5344",
    "3614",
    "2224"
  ],
  "DANC": [
    "2014",
    "2024",
    "2104",
    "3024",
    "2004"
  ],
  "DASC": [
    "2474",
    "2484",
    "2964",
    "2974",
    "3134",
    "4374",
    "4474",
    "4475",
    "4664",
    "4964",
    "4974",
    "4994",
    "5004",
    "5904",
    "5974",
    "5994"
  ],
  "ECE": [
    "1004",
    "2024",
    "2054",
    "2164",
    "2214",
    "2514",
    "2544",
    "2564",
    "2714",
    "2804",
    "2974",
    "2994",
    "3004",
    "3054",
    "3074",
    "3105",
    "3106",
    "3134",
    "3204",
    "3214",
    "3254",
    "3274",
    "3304",
    "3354",
    "3504",
    "3514",
    "3544",
    "3564",
    "3574",
    "3604",
    "3614",
    "3704",
    "3714",
    "4114",
    "4124",
    "4174",
    "4254",
    "4314",
    "4354",
    "4364",
    "4424",
    "4514",
    "4524",
    "4550",
    "4560",
    "4564",
    "4644",
    "4704",
    "4805",
    "4806",
    "4944",
    "4974",
    "4994",
    "5106",
    "5174",
    "5205",
    "5210",
    "5224",
    "5274",
    "5374G",
    "5404",
    "5424",
    "5434",
    "5444",
    "5464",
    "5480",
    "5484",
    "5494",
    "5544",
    "5545",
    "5550G",
    "5560",
    "5566",
    "5580",
    "5586",
    "5590",
    "5606",
    "5620",
    "5654",
    "5664",
    "5714",
    "5734",
    "5764",
    "5904",
    "5944",
    "5974",
    "5994",
    "6116",
    "6524",
    "6744",
    "6774",
    "7994",
    "4234",
    "5636",
    "4144",
    "5344",
    "5284",
    "5244",
    "4984",
    "6504",
    "5634",
    "5984"
  ],
  "ECON": [
    "1104",
    "1204",
    "2005",
    "2006",
    "2974",
    "2974H",
    "2994",
    "3024",
    "3054",
    "3104",
    "3134",
    "3154",
    "3204",
    "3214",
    "3254",
    "4214",
    "4304",
    "4314",
    "4424",
    "4434",
    "4614",
    "4754",
    "4964",
    "4974",
    "4974H",
    "4994",
    "4994H",
    "5006",
    "5126",
    "5314G",
    "5945",
    "5964",
    "5974",
    "5994",
    "6004",
    "6024",
    "6614",
    "6994",
    "7994",
    "5016",
    "4135",
    "4054",
    "3144",
    "5154",
    "3034",
    "1214",
    "6564",
    "4864"
  ],
  "EDCI": [
    "1004",
    "2004",
    "2574",
    "2614",
    "3024",
    "3144",
    "3334",
    "4244",
    "4454",
    "4734",
    "4744",
    "4964",
    "4974",
    "4994",
    "5104",
    "5204",
    "5264",
    "5554",
    "5604",
    "5704",
    "5744",
    "5754",
    "5764",
    "5774",
    "5784",
    "5824",
    "5894",
    "5904",
    "5964",
    "5974",
    "5994",
    "6024",
    "6944",
    "7754",
    "7964",
    "7994",
    "5854",
    "6444",
    "5304",
    "5404",
    "4724",
    "3354",
    "4074",
    "6164",
    "2464"
  ],
  "EDCO": [
    "2004",
    "6524",
    "7994",
    "6324"
  ],
  "EDCT": [
    "4964",
    "5634",
    "5684",
    "5784",
    "5964",
    "5974",
    "7994",
    "4624"
  ],
  "EDEL": [
    "5614",
    "6104",
    "6114",
    "6134",
    "6924",
    "7704",
    "7714",
    "7994",
    "5024",
    "5004"
  ],
  "EDEP": [
    "2374",
    "3474",
    "5114",
    "5154",
    "5894",
    "5964",
    "5974",
    "6114",
    "6224",
    "7964",
    "7994"
  ],
  "EDHE": [
    "5106",
    "5284",
    "5334",
    "5604",
    "5974",
    "6054",
    "6274",
    "6974",
    "7714",
    "7994",
    "6044",
    "6404"
  ],
  "EDIT": [
    "5154",
    "5164",
    "5224",
    "5274",
    "5534",
    "5564",
    "5584",
    "5604",
    "5614",
    "5624",
    "5654",
    "5774",
    "5784",
    "5904",
    "5974",
    "6334",
    "6944",
    "7994"
  ],
  "EDP": [
    "5974",
    "7994"
  ],
  "EDRE": [
    "5644",
    "5974",
    "6504",
    "6524",
    "6606",
    "6974",
    "7714",
    "7964",
    "7994"
  ],
  "EDTE": [
    "1004",
    "5974",
    "1014"
  ],
  "ENGE": [
    "1014",
    "1215",
    "1216",
    "2634",
    "2964",
    "2974",
    "2994",
    "4094",
    "4736",
    "4964",
    "4994",
    "5304",
    "5514",
    "5704",
    "5974",
    "5994",
    "6614",
    "6624",
    "6974",
    "7994",
    "6714",
    "1004"
  ],
  "ENGL": [
    "1105",
    "1106",
    "1504",
    "1514",
    "1524",
    "1614",
    "1624",
    "1654",
    "1704",
    "2014",
    "2034",
    "2534",
    "2544",
    "2604",
    "2634",
    "2664",
    "2724",
    "2744",
    "2814",
    "2844",
    "2964",
    "2974",
    "2974H",
    "3134",
    "3434",
    "3544",
    "3684",
    "3704",
    "3714",
    "3724",
    "3734",
    "3734H",
    "3744",
    "3744H",
    "3764",
    "3774",
    "3804",
    "3814",
    "3824",
    "3834",
    "3844",
    "3900",
    "3954",
    "4084",
    "4164",
    "4204",
    "4514",
    "4704",
    "4784",
    "4814",
    "4824",
    "4874",
    "4964",
    "4974",
    "4974H",
    "4994",
    "4994H",
    "5024",
    "5034",
    "5084",
    "5734",
    "5774",
    "5894",
    "5974",
    "5994",
    "6704",
    "6714",
    "7994",
    "4074",
    "6334",
    "4804",
    "5674",
    "2434",
    "3364",
    "5054",
    "4714",
    "5074",
    "5554",
    "3324",
    "2444",
    "1714",
    "3784",
    "2644",
    "3315"
  ],
  "ENGR": [
    "1034",
    "1054",
    "2004A",
    "2004E",
    "2004R",
    "2004S",
    "2044",
    "2464",
    "3124",
    "3954",
    "4134",
    "4974",
    "5204"
  ],
  "ENSC": [
    "1016",
    "3134",
    "4164",
    "4244",
    "4314",
    "4344",
    "4414",
    "4734",
    "4774",
    "5244"
  ],
  "ENT": [
    "2004",
    "2254",
    "2264",
    "2974",
    "3254",
    "3264",
    "4254",
    "4354",
    "4624",
    "4974",
    "4994",
    "5004",
    "5624",
    "5904",
    "5974",
    "5994",
    "6004",
    "7994",
    "6164"
  ],
  "ESM": [
    "2104",
    "2114",
    "2204",
    "2304",
    "2974",
    "2994",
    "3054",
    "3064",
    "4024",
    "4084",
    "4106",
    "4224",
    "4304",
    "4404",
    "4444",
    "4904",
    "4974",
    "4974H",
    "4994",
    "4994H",
    "5004",
    "5054",
    "5144",
    "5174",
    "5305",
    "5414",
    "5454",
    "5894",
    "5904",
    "5944",
    "5974",
    "5994",
    "6254",
    "6974",
    "7994",
    "4245",
    "5245G",
    "5314",
    "6314",
    "5304",
    "6164"
  ],
  "FIN": [
    "2114",
    "2164",
    "3054",
    "3074",
    "3104",
    "3114",
    "3124",
    "3134",
    "3144",
    "3154",
    "3174",
    "3254",
    "4004",
    "4014",
    "4124",
    "4134",
    "4144",
    "4154",
    "4214",
    "4224",
    "4225",
    "4226",
    "4234",
    "4244",
    "4254",
    "4255",
    "4256",
    "4264",
    "4274",
    "4275",
    "4276",
    "4314",
    "5024",
    "5654",
    "6126",
    "7994"
  ],
  "FIW": [
    "2114",
    "2314",
    "2324",
    "2514",
    "2964",
    "2974",
    "2994",
    "3954",
    "3964",
    "4114",
    "4214",
    "4314",
    "4324",
    "4344",
    "4424",
    "4434",
    "4454",
    "4474",
    "4614",
    "4624",
    "4714",
    "4964",
    "4974",
    "4994",
    "5714G",
    "5774",
    "5894",
    "5974",
    "5994",
    "6004",
    "7994",
    "5514"
  ],
  "FL": [
    "2964",
    "2974",
    "4964",
    "4974",
    "4974H",
    "4994",
    "4994H",
    "5974",
    "5114"
  ],
  "FMD": [
    "1204",
    "2204",
    "2214",
    "2224",
    "2264",
    "3034",
    "3204",
    "3224",
    "4234",
    "4264",
    "4274",
    "4964",
    "4974",
    "4994",
    "4014",
    "3264"
  ],
  "FR": [
    "1106",
    "2106",
    "2164",
    "2964",
    "2974",
    "3106",
    "3126",
    "3154",
    "3304",
    "4154",
    "4794",
    "4964",
    "4974",
    "4974H",
    "4994",
    "4994H",
    "5974",
    "5994",
    "3444",
    "5404",
    "1114",
    "2714",
    "4314"
  ],
  "FREC": [
    "1004",
    "2004",
    "2114",
    "2124",
    "2214",
    "2324",
    "2414",
    "2554",
    "2614",
    "2974",
    "2994",
    "3044",
    "3214",
    "3224",
    "3324",
    "3364",
    "3524",
    "3544",
    "3724",
    "3734",
    "3954",
    "3964",
    "4044",
    "4214",
    "4244",
    "4324",
    "4434",
    "4444",
    "4454",
    "4464",
    "4554",
    "4784",
    "4964",
    "4974",
    "4994",
    "5004",
    "5104",
    "5144",
    "5244G",
    "5254",
    "5454G",
    "5784G",
    "5884",
    "5894",
    "5904",
    "5974",
    "5994",
    "7994",
    "5044",
    "5034",
    "2254",
    "4984",
    "3984",
    "4714",
    "5154",
    "4134"
  ],
  "FST": [
    "2004",
    "2014",
    "2024",
    "2044",
    "2974",
    "2994",
    "3024",
    "3114",
    "3124",
    "3514",
    "3604",
    "4014",
    "4104",
    "4204",
    "4524",
    "4544",
    "4974",
    "4994",
    "5004",
    "5014",
    "5604",
    "5664",
    "5904",
    "5974",
    "5994",
    "7994",
    "5614"
  ],
  "GBCB": [
    "5004",
    "5874",
    "5974",
    "7994"
  ],
  "GEOG": [
    "1014",
    "1084",
    "1104",
    "1116",
    "1504",
    "2054",
    "2064",
    "2084",
    "2104",
    "2244",
    "2506",
    "2784",
    "2964",
    "2974",
    "3034",
    "3104",
    "3244",
    "3274",
    "3304",
    "3314",
    "3504",
    "3516",
    "4054",
    "4074",
    "4084",
    "4224",
    "4314",
    "4354",
    "4414",
    "4444",
    "4524",
    "4554",
    "4964",
    "4974",
    "4994",
    "5004",
    "5034",
    "5064",
    "5074G",
    "5084G",
    "5104",
    "5224G",
    "5354G",
    "5414G",
    "5424",
    "5894",
    "5904",
    "5974",
    "5994",
    "7994",
    "1024",
    "2074",
    "4394",
    "5984",
    "4984",
    "3844",
    "1004",
    "4094",
    "5094G",
    "5154"
  ],
  "GEOS": [
    "1004",
    "1014",
    "1024",
    "1034",
    "1064",
    "1104",
    "1124",
    "2004",
    "2104",
    "2444",
    "2964",
    "2994",
    "3014",
    "3034",
    "3104",
    "3304",
    "3604",
    "3704",
    "4024",
    "4084",
    "4354",
    "4624",
    "4804",
    "4824",
    "4924",
    "4974",
    "4994",
    "5044",
    "5084G",
    "5154",
    "5354G",
    "5804G",
    "5924G",
    "5974",
    "5994",
    "6204",
    "6304",
    "7994",
    "4154",
    "4244",
    "5244",
    "4614",
    "5614",
    "5124",
    "5214",
    "5054"
  ],
  "GER": [
    "1106",
    "2106",
    "2964",
    "2974",
    "2974H",
    "3106",
    "3306",
    "3474",
    "4334",
    "4794",
    "4964",
    "4974",
    "4974H",
    "4994",
    "4994H",
    "5334G",
    "5974",
    "5994"
  ],
  "GIA": [
    "5004",
    "5034",
    "5116",
    "5254",
    "5274",
    "5404",
    "5904",
    "5964",
    "5974",
    "5994",
    "7994",
    "5444",
    "6214",
    "5424",
    "5484"
  ],
  "GR": [
    "1106",
    "2114",
    "2964",
    "2974",
    "2974H",
    "4964",
    "4974",
    "4974H",
    "4994",
    "4994H",
    "6974"
  ],
  "GRAD": [
    "5004",
    "5014",
    "5024",
    "5034",
    "5104",
    "5114",
    "5124",
    "5134",
    "5144",
    "5204",
    "5214",
    "5516",
    "5904",
    "5944",
    "5954",
    "5964",
    "5974",
    "5994",
    "7944",
    "7994"
  ],
  "HD": [
    "1004",
    "1134",
    "2004",
    "2014",
    "2104",
    "2304",
    "2314",
    "2335",
    "2336",
    "3014",
    "3024",
    "3144",
    "3224",
    "3254",
    "4324",
    "4714",
    "4964",
    "4974H",
    "4994",
    "5254",
    "5524",
    "5714",
    "5754",
    "5964",
    "5974",
    "5994",
    "6004",
    "7994",
    "3114",
    "3304",
    "5224",
    "5654",
    "6414"
  ],
  "HEB": [
    "2974H",
    "4974H",
    "4994H"
  ],
  "HIST": [
    "1025",
    "1115",
    "1116",
    "1215",
    "1216",
    "2004",
    "2054",
    "2124",
    "2276",
    "2356",
    "2604",
    "2724",
    "2964",
    "2974",
    "2974H",
    "3014",
    "3254",
    "3304",
    "3534",
    "3564",
    "3914",
    "4004",
    "4914",
    "4964",
    "4974",
    "4974H",
    "4994",
    "4994H",
    "5134",
    "5414",
    "5894",
    "5904",
    "5964",
    "5974",
    "5994",
    "5484",
    "3705",
    "1084",
    "3504",
    "5424",
    "3054",
    "3544",
    "3984",
    "1764",
    "1026",
    "2346",
    "2494",
    "3106",
    "3144",
    "3314",
    "3344",
    "3484",
    "3614",
    "3714",
    "3774",
    "2104",
    "3734",
    "2184",
    "2224",
    "2234",
    "5984"
  ],
  "HNFE": [
    "1004",
    "1214",
    "2004",
    "2014",
    "2014H",
    "2104",
    "2204",
    "2264",
    "2314",
    "2334",
    "2484",
    "2664",
    "2774",
    "2804",
    "2824",
    "2974",
    "2994",
    "3024",
    "3034",
    "3224",
    "3634",
    "3804",
    "4004",
    "4026",
    "4126",
    "4174",
    "4224",
    "4644",
    "4754",
    "4774",
    "4824",
    "4844",
    "4954",
    "4964",
    "4974",
    "4994",
    "4994H",
    "5126G",
    "5144",
    "5214",
    "5314",
    "5324",
    "5334",
    "5344",
    "5394",
    "5454",
    "5694",
    "5754",
    "5904",
    "5964",
    "5974",
    "5994",
    "7994",
    "5414",
    "1216",
    "4804",
    "4025",
    "2274"
  ],
  "HORT": [
    "2164",
    "2234",
    "2244",
    "2304",
    "3114",
    "3326",
    "4206",
    "4344",
    "4546",
    "4554",
    "4614",
    "4784",
    "4764",
    "5784G"
  ],
  "HTM": [
    "1414",
    "2314",
    "2434",
    "2454",
    "2464",
    "2514",
    "2974",
    "3044",
    "3414",
    "3424",
    "3444",
    "3484",
    "3524",
    "3954",
    "4354",
    "4414",
    "4434",
    "4444",
    "4454",
    "4464",
    "4484",
    "4964",
    "4974",
    "4994",
    "5024",
    "5424",
    "5444",
    "5554",
    "5564",
    "5944",
    "5964",
    "5974",
    "5994",
    "6434",
    "6974",
    "7994",
    "3244",
    "2474",
    "2104"
  ],
  "HUM": [
    "2974",
    "2974H",
    "4974",
    "4974H",
    "4994",
    "4994H",
    "5904",
    "5974",
    "5994",
    "1054",
    "1324",
    "1504",
    "1604",
    "1704",
    "2204",
    "2504",
    "3204",
    "4414",
    "4104",
    "5204",
    "1984A"
  ],
  "IDS": [
    "1114",
    "2016",
    "2044",
    "2124",
    "2304",
    "3016",
    "3204",
    "3224",
    "3234",
    "3900",
    "4015",
    "4016",
    "4094",
    "4964",
    "4974",
    "4994"
  ],
  "IS": [
    "1004",
    "1024",
    "1034",
    "2004",
    "2044",
    "2054",
    "2064",
    "2084",
    "2964",
    "2974",
    "2974H",
    "3004",
    "3034",
    "3104",
    "3114",
    "3115",
    "3126",
    "3134",
    "3136",
    "3344",
    "3615",
    "3616",
    "3624",
    "3734",
    "3796",
    "3954",
    "4014",
    "4024",
    "4034",
    "4064",
    "4736",
    "4744",
    "4754",
    "4964",
    "4974",
    "4974H",
    "4994",
    "4994H",
    "1104",
    "3064",
    "3135",
    "3044",
    "3644",
    "4054",
    "3634",
    "4004",
    "3584",
    "3626",
    "3844"
  ],
  "ISC": [
    "1006",
    "1106H",
    "1116",
    "2106H",
    "2116"
  ],
  "ISE": [
    "2004",
    "2014",
    "2024",
    "2034",
    "2214",
    "2404",
    "2974",
    "2994",
    "3004",
    "3034",
    "3424B",
    "3424",
    "3614",
    "3624",
    "4006",
    "4204",
    "4264",
    "4304",
    "4654",
    "4804",
    "4974",
    "4994",
    "5016",
    "5054",
    "5134",
    "5174",
    "5406",
    "5414",
    "5454",
    "5624",
    "5714",
    "5734",
    "5834",
    "5874",
    "5904",
    "5974",
    "5994",
    "6574",
    "7994",
    "2804",
    "5114",
    "5644",
    "5674",
    "5844",
    "6024",
    "6454",
    "6614"
  ],
  "ITAL": [
    "1105",
    "1106",
    "1204",
    "2106",
    "2964",
    "2974",
    "2974H",
    "4964",
    "4974",
    "4974H",
    "4994",
    "4994H",
    "3305",
    "3954"
  ],
  "ITDS": [
    "1114",
    "1224",
    "2054",
    "2134",
    "3054",
    "3126",
    "3176",
    "3184",
    "4054",
    "4964",
    "4974",
    "4994",
    "2224"
  ],
  "JMC": [
    "2074",
    "3154",
    "3174",
    "3254",
    "3314",
    "3324",
    "3334",
    "3344",
    "4064",
    "4254",
    "4264",
    "4274",
    "4334",
    "4814",
    "4824",
    "4834",
    "2034",
    "4114",
    "4144"
  ],
  "JPN": [
    "1106",
    "2106",
    "2964",
    "2974",
    "2974H",
    "3106",
    "3126",
    "4964",
    "4974",
    "4974H",
    "4994H",
    "5974",
    "3474",
    "1114"
  ],
  "JUD": [
    "2974",
    "2974H",
    "4974",
    "4974H",
    "4994",
    "4994H",
    "2134"
  ],
  "LAHS": [
    "1014",
    "2724",
    "3954G",
    "2104"
  ],
  "LAR": [
    "1254",
    "2016",
    "2554",
    "3016",
    "3044",
    "3164",
    "3264",
    "4014",
    "4034",
    "4094",
    "4554",
    "4706",
    "4964",
    "4974",
    "4974H",
    "4994",
    "5006",
    "5014G",
    "5034G",
    "5044",
    "5704",
    "5724",
    "5774",
    "5974",
    "5994",
    "7994",
    "1014",
    "2026",
    "3154"
  ],
  "LAT": [
    "1106",
    "2964",
    "2974",
    "2974H",
    "3004",
    "4964",
    "4974",
    "4974H",
    "4994",
    "4994H",
    "5974",
    "1105"
  ],
  "LDRS": [
    "1414",
    "1424",
    "2014",
    "2964",
    "2974",
    "3304",
    "3954",
    "4044",
    "4514",
    "4754",
    "4964",
    "4974",
    "4994",
    "5004",
    "5454",
    "5464",
    "5554",
    "5904",
    "5974",
    "4984"
  ],
  "MACR": [
    "5004",
    "5016",
    "5024",
    "5974",
    "5994",
    "7994"
  ],
  "MATH": [
    "1014",
    "1025",
    "1026",
    "1044",
    "1214",
    "1225",
    "1226",
    "1524",
    "1536",
    "1614",
    "1624",
    "2114",
    "2114H",
    "2204",
    "2204H",
    "2214",
    "2214H",
    "2406H",
    "2534",
    "2974",
    "2974H",
    "2994",
    "2994H",
    "3034",
    "3124",
    "3134",
    "3144",
    "3214",
    "3224",
    "3414",
    "4134",
    "4144",
    "4175",
    "4176",
    "4226",
    "4234",
    "4254",
    "4324",
    "4334",
    "4404",
    "4414",
    "4426",
    "4445",
    "4446",
    "4454",
    "4564",
    "4574",
    "4626",
    "4754",
    "4974",
    "4974H",
    "4994",
    "4994H",
    "5114",
    "5126",
    "5235",
    "5254",
    "5414",
    "5425",
    "5464",
    "5484",
    "5486",
    "5516",
    "5524",
    "5554",
    "5974",
    "5994",
    "7994",
    "6324",
    "5624",
    "5546",
    "5226",
    "5174",
    "5214",
    "5514"
  ],
  "ME": [
    "2004",
    "2134",
    "2974",
    "2994",
    "3024",
    "3034",
    "3304",
    "3414B",
    "3414",
    "3524",
    "3534",
    "3534B",
    "3604",
    "3624",
    "3624B",
    "4005B",
    "4005",
    "4016",
    "4034",
    "4174",
    "4184",
    "4454",
    "4534",
    "4614",
    "4634",
    "4644",
    "4654",
    "4974",
    "4994",
    "5034",
    "5214",
    "5314",
    "5414",
    "5424",
    "5564",
    "5584",
    "5644",
    "5714",
    "5734",
    "5804",
    "5904",
    "5944",
    "5974",
    "5994",
    "6544",
    "6574",
    "7994",
    "5454",
    "5104",
    "5694"
  ],
  "MGT": [
    "1104",
    "1936",
    "1946",
    "2064",
    "2104",
    "2114",
    "2314",
    "2354",
    "2614",
    "2936",
    "2946",
    "3064",
    "3074",
    "3094",
    "3304",
    "3324",
    "3334",
    "3404",
    "3424",
    "3444",
    "3604",
    "3614",
    "3754",
    "3804",
    "3936",
    "3946",
    "3954",
    "3964",
    "4064",
    "4084",
    "4094",
    "4334",
    "4344",
    "4354",
    "4394",
    "4414",
    "4936",
    "4946",
    "4964",
    "4974",
    "4994",
    "4994H",
    "5594",
    "5804",
    "5854",
    "5905",
    "5974",
    "5994",
    "6224",
    "6704",
    "6944",
    "7994",
    "3414",
    "5964",
    "2945"
  ],
  "MINE": [
    "2114",
    "2504",
    "2544",
    "2564",
    "2994",
    "3564",
    "3574",
    "3584",
    "3644",
    "4636",
    "4644",
    "4974",
    "4994",
    "5214",
    "5904",
    "5944",
    "5974",
    "5994",
    "7994"
  ],
  "MKTG": [
    "2104",
    "3104",
    "3104H",
    "3134",
    "3164",
    "3504",
    "4154",
    "4164",
    "4204",
    "4254",
    "4264",
    "4304",
    "4354",
    "4404",
    "4454",
    "4554",
    "4604",
    "4644",
    "4704",
    "4734",
    "4754",
    "4774",
    "4974",
    "4994",
    "4994H",
    "5154",
    "5264",
    "5444",
    "5704",
    "5894",
    "5904",
    "5964",
    "5974",
    "5994",
    "6244",
    "7994",
    "6106",
    "6204",
    "4054",
    "4174",
    "4114"
  ],
  "MN": [
    "1014",
    "2004",
    "2104",
    "3005",
    "4006"
  ],
  "MS": [
    "1006",
    "2006",
    "3006",
    "4005",
    "4006",
    "4964"
  ],
  "MSE": [
    "1014",
    "2034",
    "2054",
    "2114",
    "2994",
    "3044",
    "3054",
    "3064",
    "3304",
    "3314",
    "3354",
    "3884",
    "4076",
    "4086",
    "4096H",
    "4314",
    "4324",
    "4334",
    "4544",
    "4554",
    "4574",
    "4644",
    "4974",
    "4994",
    "4994H",
    "5016",
    "5034",
    "5064",
    "5144",
    "5304",
    "5334",
    "5574G",
    "5904",
    "5974",
    "5994",
    "7994",
    "5504",
    "6214",
    "5174",
    "5124",
    "4234"
  ],
  "MTRG": [
    "2964",
    "2974",
    "3954",
    "4584",
    "4964",
    "4974",
    "4994"
  ],
  "MUS": [
    "1005",
    "1006",
    "1104",
    "2026",
    "2046",
    "2054",
    "2056",
    "2066",
    "2116",
    "2214",
    "2234",
    "2244",
    "2514",
    "2524",
    "2534",
    "2544",
    "2554",
    "2564",
    "2574",
    "2584",
    "2594",
    "2614",
    "2624",
    "2634",
    "2644",
    "2654",
    "2664",
    "2674",
    "2684",
    "2734",
    "2754",
    "2816",
    "2974",
    "2974H",
    "3026",
    "3036",
    "3046",
    "3054",
    "3056",
    "3066",
    "3164H",
    "3174",
    "3194",
    "3214",
    "3226",
    "3314",
    "3414",
    "3814",
    "3815",
    "4056",
    "4174",
    "4514",
    "4524",
    "4534",
    "4544",
    "4554",
    "4564",
    "4574",
    "4584",
    "4594",
    "4614",
    "4624",
    "4634",
    "4644",
    "4654",
    "4664",
    "4674",
    "4684",
    "4734",
    "4744",
    "4754",
    "4764",
    "4964",
    "4974",
    "4974H",
    "4994",
    "4994H",
    "5314",
    "5414",
    "5514",
    "5534",
    "5564",
    "5574",
    "5584",
    "5594",
    "5634",
    "5684",
    "5744",
    "5974",
    "1114",
    "1134",
    "2224",
    "2344",
    "1124"
  ],
  "NANO": [
    "1016",
    "2024",
    "2814",
    "3016",
    "3124",
    "4124",
    "4334",
    "4354",
    "4994"
  ],
  "NEUR": [
    "2025",
    "2026",
    "2035",
    "2036",
    "2464",
    "2594",
    "2974",
    "2994",
    "3034",
    "3044",
    "3054",
    "3084",
    "3144",
    "3554",
    "3844",
    "3914",
    "4034",
    "4044",
    "4064",
    "4514",
    "4594",
    "4814",
    "4914",
    "4974",
    "4994",
    "4994H",
    "5024",
    "5074",
    "5514G",
    "5814G",
    "5844",
    "5914",
    "5994",
    "7994",
    "2364",
    "6034"
  ],
  "NR": [
    "1116",
    "2554",
    "2974",
    "3954",
    "3964",
    "4106",
    "4444",
    "4974",
    "4994",
    "5014",
    "5114",
    "5174",
    "5184",
    "5284",
    "5434",
    "5724",
    "5814",
    "5824",
    "5854",
    "5874",
    "5254",
    "5154",
    "5954",
    "5974",
    "6104",
    "5524"
  ],
  "NSEG": [
    "3146",
    "4204",
    "4974",
    "4994",
    "4994H",
    "5124",
    "5204",
    "5504",
    "5604",
    "5904",
    "5944",
    "5974",
    "5994",
    "7994",
    "6334"
  ],
  "PAPA": [
    "5034",
    "5254",
    "5315",
    "5784",
    "5904",
    "5954",
    "5974",
    "5994",
    "6154",
    "6224",
    "6294",
    "6314",
    "6394",
    "6514",
    "7964",
    "7994",
    "6414"
  ],
  "PHIL": [
    "1204",
    "1304",
    "1504",
    "2116",
    "2126",
    "2304",
    "2314",
    "2964",
    "2974",
    "2974H",
    "3015",
    "3016",
    "3324",
    "3334",
    "3505",
    "4014",
    "4974",
    "4974H",
    "4994",
    "4994H",
    "5904",
    "5974",
    "5994",
    "6014",
    "3614",
    "4224",
    "4614",
    "5505"
  ],
  "PHS": [
    "1514",
    "2004",
    "2974",
    "2974H",
    "2994",
    "2994H",
    "3014",
    "3064",
    "3534",
    "3634",
    "4014",
    "4044",
    "4054",
    "4064",
    "4074",
    "4974",
    "4974H",
    "4994",
    "4994H",
    "5004",
    "5034",
    "5044",
    "5064",
    "5254",
    "5314",
    "5724",
    "5904",
    "5924",
    "5934",
    "5935",
    "5936",
    "5974",
    "3074",
    "1004",
    "3654"
  ],
  "PHYS": [
    "1056",
    "1156",
    "2205",
    "2206",
    "2215",
    "2216",
    "2305",
    "2305B",
    "2306B",
    "2306",
    "2326",
    "2404",
    "2504",
    "2964",
    "2974",
    "2974H",
    "2994",
    "2994H",
    "3154",
    "3254",
    "3314",
    "3406",
    "3656",
    "3684",
    "3704",
    "4254",
    "4316",
    "4455",
    "4524",
    "4564",
    "4574",
    "4654",
    "4674",
    "4684",
    "4714",
    "4774",
    "4964",
    "4974",
    "4974H",
    "4994",
    "4994H",
    "5254G",
    "5406",
    "5455",
    "5464",
    "5524G",
    "5556",
    "5564G",
    "5574G",
    "5654G",
    "5674G",
    "5705",
    "5714G",
    "5944",
    "5974",
    "5994",
    "7994"
  ],
  "PM": [
    "2664",
    "2684",
    "3674",
    "3684",
    "4684",
    "4694",
    "4744",
    "4914",
    "4964",
    "4974",
    "4994"
  ],
  "PORT": [
    "2964",
    "2974",
    "4964",
    "4974",
    "4994"
  ],
  "PPE": [
    "2024",
    "2894",
    "3016",
    "3024",
    "4884",
    "4964",
    "4994",
    "3900",
    "1214"
  ],
  "PPWS": [
    "2004",
    "4104",
    "5054",
    "5204",
    "5344",
    "5894",
    "2104",
    "5234",
    "5534"
  ],
  "PR": [
    "2044",
    "3014",
    "3144",
    "3324",
    "4304",
    "4404",
    "4414",
    "5534",
    "5594",
    "5724",
    "3034",
    "3084"
  ],
  "PSCI": [
    "1004",
    "1014",
    "1024",
    "1034",
    "2014",
    "2024",
    "2044",
    "2054",
    "2064",
    "2084",
    "2164",
    "2974",
    "2974H",
    "3004",
    "3015",
    "3016",
    "3034",
    "3104",
    "3114",
    "3115",
    "3126",
    "3134",
    "3136",
    "3254",
    "3314",
    "3344",
    "3364",
    "3444",
    "3615",
    "3616",
    "3624",
    "3684",
    "3734",
    "3744",
    "3796",
    "4024",
    "4034",
    "4064",
    "4164",
    "4736",
    "4744",
    "4754",
    "4964",
    "4974",
    "4974H",
    "4994",
    "4994H",
    "5116",
    "5124",
    "5154",
    "5254",
    "5894",
    "5974",
    "5994",
    "5444",
    "6214",
    "5424",
    "5334",
    "5484",
    "3064",
    "3256",
    "1084",
    "3135",
    "3044",
    "4054",
    "3424",
    "3634",
    "3274",
    "2074",
    "3584",
    "3626",
    "3844"
  ],
  "PSVP": [
    "2044",
    "4104",
    "4974",
    "4994",
    "4444",
    "4484"
  ],
  "PSYC": [
    "1004",
    "1094",
    "1524",
    "2034",
    "2044",
    "2054",
    "2064",
    "2084",
    "2964",
    "2974",
    "2974H",
    "2994",
    "2994H",
    "3014",
    "3034",
    "4024",
    "4034",
    "4084",
    "4194",
    "4234",
    "4284",
    "4364",
    "4964",
    "4974",
    "4974H",
    "4994",
    "4994H",
    "5966",
    "5974",
    "5994",
    "6254",
    "6944",
    "6966",
    "7964",
    "7994",
    "3054",
    "5114",
    "5404",
    "6014",
    "6244",
    "6924",
    "4244",
    "4044",
    "4064"
  ],
  "REAL": [
    "1014",
    "2004",
    "2034",
    "2044",
    "3024",
    "3034",
    "3044",
    "4054",
    "4064",
    "4074",
    "4075",
    "4076",
    "4754",
    "4974",
    "3954",
    "4044"
  ],
  "RED": [
    "1604",
    "2234",
    "2644",
    "2654",
    "3624",
    "3674",
    "4604",
    "4654",
    "4664",
    "4964",
    "4974",
    "4994"
  ],
  "RLCL": [
    "2974",
    "2974H",
    "4974H",
    "4994",
    "4994H",
    "5974",
    "1014",
    "1044",
    "1054",
    "1084",
    "1134",
    "1504",
    "1904",
    "2004",
    "2124",
    "2134",
    "2204",
    "2464",
    "2504",
    "3204",
    "3224",
    "3414",
    "3504",
    "4324",
    "3644",
    "5124",
    "4104",
    "5204",
    "2434",
    "2444"
  ],
  "RUS": [
    "1106",
    "1114",
    "2106",
    "2114",
    "2964",
    "2974",
    "2974H",
    "3105",
    "3106",
    "3124",
    "3314",
    "3434",
    "3954",
    "4204",
    "4304",
    "4964",
    "4974",
    "4974H",
    "4994",
    "4994H",
    "1105",
    "2734",
    "3984"
  ],
  "SBIO": [
    "1114",
    "2004",
    "2104",
    "2314",
    "2614",
    "2964",
    "2974",
    "2994",
    "3004",
    "3124",
    "3314",
    "3434",
    "3444",
    "3446",
    "3464",
    "3554",
    "3954",
    "3964",
    "3994",
    "4054",
    "4224",
    "4424",
    "4714",
    "4964",
    "4974",
    "4994",
    "5004",
    "5344",
    "5424G",
    "5894",
    "5974",
    "5994",
    "7994",
    "3104",
    "2984",
    "4984",
    "5984",
    "3244",
    "3005",
    "3014",
    "4384"
  ],
  "SOC": [
    "1004",
    "2004",
    "2024",
    "2104",
    "2264",
    "2304",
    "2404",
    "2604",
    "2974",
    "2974H",
    "3004",
    "3104",
    "3204",
    "3504",
    "3714",
    "3854",
    "3954",
    "4044",
    "4114",
    "4194",
    "4404",
    "4414",
    "4454",
    "4704",
    "4714",
    "4754",
    "4964",
    "4974",
    "4974H",
    "4994",
    "4994H",
    "5224",
    "5234",
    "5894",
    "5974",
    "5994",
    "6214",
    "7994",
    "1084",
    "2014",
    "3014",
    "3404",
    "4014",
    "4444",
    "5114",
    "5714",
    "4324",
    "6454",
    "5454"
  ],
  "SPAN": [
    "1105",
    "1106",
    "1114",
    "2105",
    "2106",
    "2964",
    "2974",
    "2974H",
    "3105",
    "3106",
    "3126",
    "3304",
    "3414",
    "3514",
    "3564",
    "4324",
    "4964",
    "4964H",
    "4974",
    "4974H",
    "4994",
    "4994H",
    "5974",
    "5994",
    "3534",
    "4344",
    "5344",
    "5324"
  ],
  "SPES": [
    "2004",
    "2244",
    "2964",
    "2974",
    "4964",
    "4974",
    "4994",
    "5004",
    "5904",
    "5974",
    "5994",
    "7994",
    "2984",
    "4114"
  ],
  "SPIA": [
    "1044",
    "2244",
    "2314",
    "3554",
    "4464",
    "4554",
    "4964",
    "4994",
    "5124",
    "5154",
    "5974",
    "6004",
    "5674",
    "5614",
    "2544",
    "6104"
  ],
  "STAT": [
    "2004",
    "2964",
    "2974H",
    "3005",
    "3006",
    "3104",
    "3204",
    "3604",
    "3615",
    "3616",
    "3654",
    "3704",
    "4004",
    "4105",
    "4106",
    "4204",
    "4214",
    "4444",
    "4504",
    "4604",
    "4654",
    "4664",
    "4705",
    "4714",
    "4744",
    "4804",
    "4964",
    "4974",
    "4974H",
    "4994",
    "4994H",
    "5024",
    "5105G",
    "5106G",
    "5114",
    "5124",
    "5204",
    "5204G",
    "5214G",
    "5414",
    "5444G",
    "5484",
    "5504G",
    "5615",
    "5616",
    "5754",
    "5894",
    "5904",
    "5924",
    "5974",
    "5994",
    "6105",
    "7994",
    "6544",
    "5526",
    "2094",
    "2274",
    "6564"
  ],
  "STL": [
    "2304",
    "4314",
    "4334",
    "4974",
    "4994"
  ],
  "STS": [
    "1504",
    "2034",
    "2054",
    "2604",
    "2664",
    "2724",
    "2974",
    "2974H",
    "3104",
    "3284",
    "3314",
    "3334",
    "4304",
    "4754",
    "4964",
    "4974",
    "4974H",
    "4994",
    "4994H",
    "5124",
    "5154",
    "5974",
    "5994",
    "7994",
    "3705",
    "5024",
    "2464",
    "2444",
    "4324",
    "6014",
    "5204",
    "2454",
    "4704",
    "5444",
    "4014",
    "3734"
  ],
  "SYSB": [
    "2034",
    "2994",
    "3036",
    "3116",
    "4066",
    "4224",
    "4994"
  ],
  "TA": [
    "2014",
    "2024",
    "2114",
    "2134",
    "2164",
    "2174",
    "2204",
    "2404",
    "2964",
    "2974",
    "2974H",
    "3014",
    "3104",
    "3106",
    "3114",
    "3124",
    "3144",
    "3154",
    "4304",
    "4315",
    "4704",
    "4964",
    "4974",
    "4974H",
    "4994",
    "4994H",
    "5016",
    "5416",
    "5426",
    "5436",
    "5704",
    "5904",
    "5974",
    "5994",
    "2414",
    "5624"
  ],
  "TBMH": [
    "4964",
    "5014",
    "5024",
    "5034",
    "5044",
    "5054",
    "5106",
    "5204",
    "5304",
    "5974",
    "5994",
    "7994"
  ],
  "UAP": [
    "1024",
    "2004",
    "3014",
    "3224",
    "3344",
    "3444",
    "3744",
    "4264",
    "4394",
    "4754",
    "4914",
    "4964",
    "4974",
    "4994",
    "5004",
    "5034",
    "5126",
    "5174",
    "5224",
    "5274",
    "5304",
    "5324",
    "5424",
    "5554",
    "5644",
    "5774",
    "5784",
    "5794",
    "5894",
    "5904",
    "5924",
    "5964",
    "5974",
    "5994",
    "7994",
    "5214"
  ],
  "UH": [
    "1404",
    "1604",
    "2124",
    "2504",
    "2514",
    "2524",
    "2544",
    "2554",
    "2744",
    "2814",
    "3204",
    "3614",
    "3856",
    "4104",
    "4504",
    "4514",
    "4856",
    "4974",
    "4994"
  ],
  "UNIV": [
    "1004",
    "2114",
    "3944",
    "3944S",
    "3944T",
    "3944U"
  ],
  "VM": [
    "7064",
    "7314",
    "8000",
    "8020",
    "8024",
    "8030",
    "8110",
    "8130",
    "8194",
    "8204",
    "8214",
    "8224",
    "8244",
    "8264",
    "8394",
    "8464",
    "8494",
    "8594",
    "8604",
    "8610",
    "8666",
    "8667",
    "8670",
    "8704",
    "8714",
    "8734",
    "8744",
    "8774",
    "8784",
    "8810",
    "8814",
    "8824",
    "8844",
    "8864",
    "8874",
    "9004",
    "9024",
    "9044",
    "9064",
    "9224",
    "9264",
    "9434",
    "9454",
    "9504",
    "9534",
    "9544",
    "9624",
    "9634",
    "9644",
    "9744",
    "9804",
    "9814",
    "9824",
    "9834",
    "9964"
  ],
  "WATR": [
    "4244",
    "4464",
    "4614",
    "4994",
    "5244G",
    "5614G"
  ],
  "WGS": [
    "1824",
    "2224",
    "2264",
    "2974",
    "3134",
    "4224",
    "4754",
    "4974",
    "4994",
    "5914",
    "5974",
    "2204",
    "5924",
    "4704"
  ]
}